actual_discord_bot/__init__.py
actual_discord_bot/bot.py
actual_discord_bot-0.1.0.dist-info/LICENSE
actual_discord_bot-0.1.0.dist-info/METADATA
actual_discord_bot-0.1.0.dist-info/WHEEL
actual_discord_bot-0.1.0.dist-info/RECORD
